tree_sitter_gcode/__init__.py
tree_sitter_gcode/__init__.pyi
tree_sitter_gcode/_binding.pyd
tree_sitter_gcode/binding.c
tree_sitter_gcode/py.typed
tree_sitter_gcode/queries/highlights.scm
tree_sitter_gcode-0.1.1.dist-info/licenses/LICENSE
tree_sitter_gcode-0.1.1.dist-info/METADATA
tree_sitter_gcode-0.1.1.dist-info/WHEEL
tree_sitter_gcode-0.1.1.dist-info/top_level.txt
tree_sitter_gcode-0.1.1.dist-info/RECORD
