Metadata-Version: 2.4
Name: tree-sitter-gcode
Version: 0.1.1
Summary: G-code grammar for tree-sitter
Author-email: ChocolateNao <andrey12q112@gmail.com>
License: MIT
Project-URL: Homepage, https://github.com/chocolatenao/tree-sitter-gcode.git
Keywords: incremental,parsing,tree-sitter,gcode
Classifier: Intended Audience :: Developers
Classifier: Topic :: Software Development :: Compilers
Classifier: Topic :: Text Processing :: Linguistic
Classifier: Typing :: Typed
Requires-Python: >=3.10
License-File: LICENSE
Provides-Extra: core
Requires-Dist: tree-sitter~=0.24; extra == "core"
Dynamic: license-file
